func_call_tracer/__init__.py
func_call_tracer/func_call_tracer.py
func_call_tracer-1.0.0.dist-info/LICENSE
func_call_tracer-1.0.0.dist-info/METADATA
func_call_tracer-1.0.0.dist-info/WHEEL
func_call_tracer-1.0.0.dist-info/top_level.txt
func_call_tracer-1.0.0.dist-info/RECORD
