Metadata-Version: 2.1
Name: func_call_tracer
Version: 1.0.0
Summary: A function call tracer for Python
Author-email: ticoli <binhua.lbh@alibaba-inc.com>
Classifier: Programming Language :: Python :: 3
Classifier: License :: OSI Approved :: MIT License
Classifier: Operating System :: OS Independent
Requires-Python: >=3.6
License-File: LICENSE
